python/__init__.py
python/sgtsnepi.py
python/test_digits.py
sgtsnepi-0.101.dist-info/LICENSE
sgtsnepi-0.101.dist-info/METADATA
sgtsnepi-0.101.dist-info/WHEEL
sgtsnepi-0.101.dist-info/top_level.txt
sgtsnepi-0.101.dist-info/RECORD
