Metadata-Version: 2.1
Name: sgtsnepi
Version: 0.101
Summary: SG-t-SNE-Π Swift Neighbor Embedding of Sparse Stochastic Graphs
Home-page: https://github.com/fcdimitr/sgtsnepi
Author: Dimitris Floros
Author-email: fcdimitr@gmail.com  
License: UNKNOWN
Platform: UNKNOWN
Classifier: Programming Language :: Python :: 3
Classifier: License :: OSI Approved :: MIT License
Classifier: Operating System :: OS Independent
License-File: LICENSE
